{
  "linklists": {
    "main": [
      {
        "title": "Home",
        "url": "/home.html"
      },
      {
        "title": "Home",
        "url": "index.html"
      },
      {
        "title": "Sweet",
        "url": "sweet.html"
      },
      {
        "title": "Link 2",
        "url": "link2.html"
      },
      {
        "title": "Nested 1",
        "url": "/nested/",
        "links": [
          {
            "title": "Nested 2",
            "url": "/nested/nested/"
          }
        ]
      }
    ]
  }
}
